MANIFEST.in
README.md
align.c
buildtree.c
bytescale.c
cluster.c
co2mco.c
command_composite.c
command_dist.c
command_dist_wrapper.c
command_set.c
command_shuffle.c
distancemat.c
dnj.c
filebuff.c
global_basic.c
hclust.c
iseq2comem.c
kssdtree.py
matrix.c
mman.c
mytime.c
nj.c
nwck.c
pherror.c
phy.c
pydnj.c
pykssd.c
pynj.c
qseqs.c
sequence.c
setup.py
str.c
tmp.c
toolutils.py
tree.c
util.c
vector.c
dnjheaders/bytescale.h
dnjheaders/dnj.h
dnjheaders/filebuff.h
dnjheaders/hclust.h
dnjheaders/matrix.h
dnjheaders/mman.h
dnjheaders/nj.h
dnjheaders/nwck.h
dnjheaders/pherror.h
dnjheaders/phy.h
dnjheaders/qseqs.h
dnjheaders/str.h
dnjheaders/threader.h
dnjheaders/tmp.h
dnjheaders/vector.h
kssdheaders/co2mco.h
kssdheaders/command_composite.h
kssdheaders/command_dist.h
kssdheaders/command_dist_wrapper.h
kssdheaders/command_set.h
kssdheaders/command_shuffle.h
kssdheaders/global_basic.h
kssdheaders/iseq2comem.h
kssdheaders/mman.h
kssdheaders/mytime.h
kssdtree.egg-info/PKG-INFO
kssdtree.egg-info/SOURCES.txt
kssdtree.egg-info/dependency_links.txt
kssdtree.egg-info/not-zip-safe
kssdtree.egg-info/requires.txt
kssdtree.egg-info/top_level.txt
njheaders/align.h
njheaders/buildtree.h
njheaders/cluster.h
njheaders/distancemat.h
njheaders/sequence.h
njheaders/tree.h
njheaders/util.h