Metadata-Version: 2.1
Name: kssdtree
Version: 2.0.8
Summary: Kssdtree is a versatile Python package for phylogenetic analysis. It also provides one-stop tree construction and visualization. It can handle DNA sequences of both fasta or fastq format, whether gzipped or not. 
Home-page: https://github.com/yhlink/kssdtree
Download-URL: https://pypi.org/project/kssdtree
Author: Hang Yang
Author-email: yhlink1207@gmail.com
Requires-Dist: pyqt5
Requires-Dist: ete3
Requires-Dist: requests
Requires-Dist: pandas
